examples/touch_reward.py
examples/touch_reward_lastrun.py
psychopy_zaci/__init__.py
psychopy_zaci/components/pellet_dispenser/__init__.py
psychopy_zaci/components/pellet_dispenser/classic/reward.png
psychopy_zaci/components/pellet_dispenser/classic/reward@2x.png
psychopy_zaci/components/pellet_dispenser/dark/reward.png
psychopy_zaci/components/pellet_dispenser/dark/reward@2x.png
psychopy_zaci/components/pellet_dispenser/light/reward.png
psychopy_zaci/components/pellet_dispenser/light/reward@2x.png
psychopy_zaci/devices/pellet_dispenser.py
psychopy_zaci-0.0.1a2.dist-info/METADATA
psychopy_zaci-0.0.1a2.dist-info/WHEEL
psychopy_zaci-0.0.1a2.dist-info/entry_points.txt
psychopy_zaci-0.0.1a2.dist-info/top_level.txt
psychopy_zaci-0.0.1a2.dist-info/RECORD
