Metadata-Version: 2.1
Name: psychopy-zaci
Version: 0.0.1a2
Summary: Extension to add support for University of Lausanne's devices such as a pellet dispenser for Vervet Monkey's.
Author-email: Alexandre Tuleu <alexandre.tuleu.2005@polytechnique.org>
License: GNU General Public License v3 (GPLv3)
Project-URL: Homepage, https://github.com/atuleu/zaci/tree/main/psychopy-zaci
Project-URL: Repository, https://github.com/atuleu/zaci
Project-URL: Issues, https://github.com/atuleu/zaci/issues?q=is%3Aissue+is%3Aopen+label%3A"psychopy"
Classifier: License :: OSI Approved :: GNU General Public License v3 (GPLv3)
Classifier: Programming Language :: Python :: 3
Classifier: Programming Language :: Python :: 3 :: Only
Classifier: Programming Language :: Python :: 3.7
Classifier: Programming Language :: Python :: 3.8
Classifier: Programming Language :: Python :: 3.9
Classifier: Programming Language :: Python :: 3.10
Classifier: Programming Language :: Python :: 3.11
Classifier: Programming Language :: Python :: Implementation :: CPython
Requires-Python: >=3.7
Requires-Dist: unil-pellet-dispenser
